src/__init__.py
src/main.py
src/test_main.py
onedev_python_project_boilerplate-0.1.2.dist-info/LICENSE.txt
onedev_python_project_boilerplate-0.1.2.dist-info/METADATA
onedev_python_project_boilerplate-0.1.2.dist-info/WHEEL
onedev_python_project_boilerplate-0.1.2.dist-info/top_level.txt
onedev_python_project_boilerplate-0.1.2.dist-info/RECORD
